{
  "invention": {
    "year": 1930,
    "inventor": "Samuel Ruben",
    "discovery": "Ruben developed the first accurate thermistor in the 1930s using semiconductor materials.",
    "evolution": [
      {
        "year": 1930,
        "event": "First thermistors developed"
      },
      {
        "year": 1960,
        "event": "Negative Temperature Coefficient Thermistor (NTC) types mass-produced for industry"
      },
      {
        "year": 1990,
        "event": "Miniature SMD thermistors common"
      }
    ]
  }
}
